jssyntax/__init__.py
jssyntax/array.py
jssyntax/tools.py
jssyntax-0.2.3.dist-info/LICENSE
jssyntax-0.2.3.dist-info/METADATA
jssyntax-0.2.3.dist-info/WHEEL
jssyntax-0.2.3.dist-info/top_level.txt
jssyntax-0.2.3.dist-info/RECORD
