Metadata-Version: 2.1
Name: jssyntax
Version: 0.2.3
Summary: Write python using js syntax
Home-page: https://github.com/canwhite/jssyntax
Author: Zack Qiao
Author-email: dangbai752716886@gmail.com
Classifier: Programming Language :: Python :: 3
Classifier: License :: OSI Approved :: MIT License
Classifier: Operating System :: OS Independent
Requires-Python: >=3.6
License-File: LICENSE
